passes_rs_py-4.0.1.dist-info/METADATA
passes_rs_py-4.0.1.dist-info/WHEEL
passes_rs_py-4.0.1.dist-info/licenses/LICENSE
passes_rs_py.libs/libgcc_s-39080030.so.1
passes_rs_py/__init__.py
passes_rs_py/passes_rs_py.cpython-313t-aarch64-linux-musl.so
passes_rs_py-4.0.1.dist-info/RECORD
