Metadata-Version: 2.4
Name: passes_rs_py
Version: 4.0.1
Classifier: Programming Language :: Rust
Classifier: Programming Language :: Python :: 3
Classifier: Operating System :: OS Independent
Classifier: License :: OSI Approved :: MIT License
License-File: LICENSE
Summary: Rust library for generate Apple Wallet Passes for iOS, WatchOS, MacOS.
Keywords: passkit,wallet,apple
Author-email: Jstyles <jstyles@styl.dev>
License: MIT
Requires-Python: >=3.12
Project-URL: Homepage, https://github.com/jontyms/neo-passes-rs
Project-URL: Repository, https://github.com/jontyms/neo-passes-rs
